testdata/__init__.py
testdata/decorators.py
testdata/descriptors.py
django_testdata-1.0.3.dist-info/LICENSE
django_testdata-1.0.3.dist-info/METADATA
django_testdata-1.0.3.dist-info/WHEEL
django_testdata-1.0.3.dist-info/top_level.txt
django_testdata-1.0.3.dist-info/RECORD
